pycspro/CaseParser.py
pycspro/DictionaryParser.py
pycspro/__init__.py
pycspro-1.1.0.dist-info/LICENSE
pycspro-1.1.0.dist-info/METADATA
pycspro-1.1.0.dist-info/WHEEL
pycspro-1.1.0.dist-info/top_level.txt
pycspro-1.1.0.dist-info/RECORD
