Metadata-Version: 2.1
Name: pycspro
Version: 1.1.0
Summary: A Python library for parsing CSPro dictionaries and cases.
Home-page: https://github.com/amestsantim/pycspro
Author: Nahom Tamerat
Author-email: nahomt@amestsantim.com
License: UNKNOWN
Platform: UNKNOWN
Classifier: Programming Language :: Python :: 3
Classifier: License :: OSI Approved :: MIT License
Classifier: Operating System :: OS Independent
Requires-Python: >=3.6
Requires-Dist: transitions
